xumm/__init__.py
xumm/client.py
xumm/error.py
xumm/util.py
xumm/ws_client.py
xumm/resource/__init__.py
xumm/resource/base.py
xumm/resource/curated_assets.py
xumm/resource/kyc_status.py
xumm/resource/oauth2.py
xumm/resource/payload.py
xumm/resource/ping.py
xumm/resource/push.py
xumm/resource/rates.py
xumm/resource/storage.py
xumm/resource/user_tokens.py
xumm/resource/xrpl_tx.py
xumm/resource/types/__init__.py
xumm/resource/types/misc.py
xumm/resource/types/meta/__init__.py
xumm/resource/types/meta/application_details.py
xumm/resource/types/meta/curated_assets_response.py
xumm/resource/types/meta/kyc_info_response.py
xumm/resource/types/meta/kyc_status_response.py
xumm/resource/types/meta/pong.py
xumm/resource/types/meta/rates_response.py
xumm/resource/types/meta/user_tokens.py
xumm/resource/types/meta/xrpl_transaction.py
xumm/resource/types/oauth2/__init__.py
xumm/resource/types/oauth2/oauth2_token_response.py
xumm/resource/types/oauth2/oauth2_user_info_response.py
xumm/resource/types/payload/__init__.py
xumm/resource/types/payload/on_payload_event.py
xumm/resource/types/payload/payload_and_subscription.py
xumm/resource/types/payload/payload_subscription.py
xumm/resource/types/payload/subscription_callback_params.py
xumm/resource/types/push/__init__.py
xumm/resource/types/push/push_event_response.py
xumm/resource/types/push/push_push_response.py
xumm/resource/types/storage/__init__.py
xumm/resource/types/storage/storage_delete_response.py
xumm/resource/types/storage/storage_get_response.py
xumm/resource/types/storage/storage_response.py
xumm/resource/types/storage/storage_set_response.py
xumm/resource/types/xumm_api/__init__.py
xumm_sdk_py-1.0.4.dist-info/LICENSE
xumm_sdk_py-1.0.4.dist-info/METADATA
xumm_sdk_py-1.0.4.dist-info/WHEEL
xumm_sdk_py-1.0.4.dist-info/top_level.txt
xumm_sdk_py-1.0.4.dist-info/RECORD
