Metadata-Version: 2.1
Name: xumm-sdk-py
Version: 1.0.4
Summary: Xumm SDK for Python
Home-page: https://github.com/XRPL-Labs/xumm-sdk-py
Author: XRPL-Labs
Author-email: support@xrpl-labs.com
License: MIT
Keywords: xrp,ledger,ripple,xumm,sdk
Classifier: Development Status :: 4 - Beta
Classifier: Intended Audience :: Developers
Classifier: License :: OSI Approved :: MIT License
Classifier: Operating System :: OS Independent
Classifier: Programming Language :: Python :: 3.6
Classifier: Programming Language :: Python :: 3.7
Classifier: Programming Language :: Python :: 3.8
Classifier: Programming Language :: Python :: 3.9
License-File: LICENSE
Requires-Dist: requests (<=2.28.2,>=2.26.0)
Requires-Dist: requests-oauthlib (>=1.3.1)
Requires-Dist: websocket-client (<=1.4.2,>=1.2.3)
Requires-Dist: six (==1.16.0)
Requires-Dist: python-dotenv (<=0.21.1,>=0.19.2)
Provides-Extra: develop
Requires-Dist: pytest (==6.2.5) ; extra == 'develop'
Requires-Dist: websockets (==9.1) ; extra == 'develop'
Requires-Dist: flake8 (==4.0.1) ; extra == 'develop'
